LICENSE.txt
MANIFEST.in
README.md
requirements.txt
setup.py
AnomalyDetector/__init__.py
AnomalyDetector/command_line.py
AnomalyDetector/predict.py
CitologyAnomalyDetector.egg-info/PKG-INFO
CitologyAnomalyDetector.egg-info/SOURCES.txt
CitologyAnomalyDetector.egg-info/dependency_links.txt
CitologyAnomalyDetector.egg-info/entry_points.txt
CitologyAnomalyDetector.egg-info/requires.txt
CitologyAnomalyDetector.egg-info/top_level.txt